{
  "name" : "iv_crdl_reference_data",
  "elements" : [
    {
      "code_list_code" : "CL017",
      "code_list_name" : "KindOfPackages",
      "rdentry" : [
        {
          "dataitem" : [
            {
              "dataitem_name" : "AdditionalInformationCode",
              "dataitem_value" : "IZ"
            },
            {
              "dataitem_name" : "RDEntryStatus_state",
              "dataitem_value" : "valid"
            },
            {
              "dataitem_name" : "RDEntryStatus_activeFrom",
              "dataitem_value" : "01-11-2025"
            },
            {
              "dataitem_name" : "Phase",
              "dataitem_value" : "NCTS"
            },
            {
              "dataitem_name" : "Domain",
              "dataitem_value" : "6"
            }
          ],
          "language" : [
            {
              "lang_code" : "en",
              "lang_desc" : "Ingots, in bundle/bunch/truss"
            }
          ]
        },
        {
          "dataitem" : [
            {
              "dataitem_name" : "AdditionalInformationCode",
              "dataitem_value" : "JB"
            },
            {
              "dataitem_name" : "RDEntryStatus_state",
              "dataitem_value" : "valid"
            },
            {
              "dataitem_name" : "RDEntryStatus_activeFrom",
              "dataitem_value" : "01-11-2025"
            },
            {
              "dataitem_name" : "Phase",
              "dataitem_value" : "NCTS"
            },
            {
              "dataitem_name" : "Domain",
              "dataitem_value" : "6"
            }
          ],
          "language" : [
            {
              "lang_code" : "en",
              "lang_desc" : "Bag, jumbo"
            }
          ]
        },
        {
          "dataitem" : [
            {
              "dataitem_name" : "AdditionalInformationCode",
              "dataitem_value" : "JC"
            },
            {
              "dataitem_name" : "RDEntryStatus_state",
              "dataitem_value" : "valid"
            },
            {
              "dataitem_name" : "RDEntryStatus_activeFrom",
              "dataitem_value" : "01-11-2025"
            },
            {
              "dataitem_name" : "Phase",
              "dataitem_value" : "NCTS"
            },
            {
              "dataitem_name" : "Domain",
              "dataitem_value" : "6"
            }
          ],
          "language" : [
            {
              "lang_code" : "en",
              "lang_desc" : "Jerrican, rectangular"
            }
          ]
        },
        {
          "dataitem" : [
            {
              "dataitem_name" : "AdditionalInformationCode",
              "dataitem_value" : "JG"
            },
            {
              "dataitem_name" : "RDEntryStatus_state",
              "dataitem_value" : "valid"
            },
            {
              "dataitem_name" : "RDEntryStatus_activeFrom",
              "dataitem_value" : "01-11-2025"
            },
            {
              "dataitem_name" : "Phase",
              "dataitem_value" : "NCTS"
            },
            {
              "dataitem_name" : "Domain",
              "dataitem_value" : "6"
            }
          ],
          "language" : [
            {
              "lang_code" : "en",
              "lang_desc" : "Jug"
            }
          ]
        },
        {
          "dataitem" : [
            {
              "dataitem_name" : "AdditionalInformationCode",
              "dataitem_value" : "JR"
            },
            {
              "dataitem_name" : "RDEntryStatus_state",
              "dataitem_value" : "valid"
            },
            {
              "dataitem_name" : "RDEntryStatus_activeFrom",
              "dataitem_value" : "01-11-2025"
            },
            {
              "dataitem_name" : "Phase",
              "dataitem_value" : "NCTS"
            },
            {
              "dataitem_name" : "Domain",
              "dataitem_value" : "6"
            }
          ],
          "language" : [
            {
              "lang_code" : "en",
              "lang_desc" : "Jar"
            }
          ]
        },
        {
          "dataitem" : [
            {
              "dataitem_name" : "AdditionalInformationCode",
              "dataitem_value" : "JT"
            },
            {
              "dataitem_name" : "RDEntryStatus_state",
              "dataitem_value" : "valid"
            },
            {
              "dataitem_name" : "RDEntryStatus_activeFrom",
              "dataitem_value" : "01-11-2025"
            },
            {
              "dataitem_name" : "Phase",
              "dataitem_value" : "NCTS"
            },
            {
              "dataitem_name" : "Domain",
              "dataitem_value" : "6"
            }
          ],
          "language" : [
            {
              "lang_code" : "en",
              "lang_desc" : "Jutebag"
            }
          ]
        },
        {
          "dataitem" : [
            {
              "dataitem_name" : "AdditionalInformationCode",
              "dataitem_value" : "JY"
            },
            {
              "dataitem_name" : "RDEntryStatus_state",
              "dataitem_value" : "valid"
            },
            {
              "dataitem_name" : "RDEntryStatus_activeFrom",
              "dataitem_value" : "01-11-2025"
            },
            {
              "dataitem_name" : "Phase",
              "dataitem_value" : "NCTS"
            },
            {
              "dataitem_name" : "Domain",
              "dataitem_value" : "6"
            }
          ],
          "language" : [
            {
              "lang_code" : "en",
              "lang_desc" : "Jerrican, cylindrical"
            }
          ]
        },
        {
          "dataitem" : [
            {
              "dataitem_name" : "AdditionalInformationCode",
              "dataitem_value" : "KG"
            },
            {
              "dataitem_name" : "RDEntryStatus_state",
              "dataitem_value" : "valid"
            },
            {
              "dataitem_name" : "RDEntryStatus_activeFrom",
              "dataitem_value" : "01-11-2025"
            },
            {
              "dataitem_name" : "Phase",
              "dataitem_value" : "NCTS"
            },
            {
              "dataitem_name" : "Domain",
              "dataitem_value" : "6"
            }
          ],
          "language" : [
            {
              "lang_code" : "en",
              "lang_desc" : "Keg"
            }
          ]
        },
        {
          "dataitem" : [
            {
              "dataitem_name" : "AdditionalInformationCode",
              "dataitem_value" : "KI"
            },
            {
              "dataitem_name" : "RDEntryStatus_state",
              "dataitem_value" : "valid"
            },
            {
              "dataitem_name" : "RDEntryStatus_activeFrom",
              "dataitem_value" : "01-11-2025"
            },
            {
              "dataitem_name" : "Phase",
              "dataitem_value" : "NCTS"
            },
            {
              "dataitem_name" : "Domain",
              "dataitem_value" : "6"
            }
          ],
          "language" : [
            {
              "lang_code" : "en",
              "lang_desc" : "Kit"
            }
          ]
        },
        {
          "dataitem" : [
            {
              "dataitem_name" : "AdditionalInformationCode",
              "dataitem_value" : "LE"
            },
            {
              "dataitem_name" : "RDEntryStatus_state",
              "dataitem_value" : "valid"
            },
            {
              "dataitem_name" : "RDEntryStatus_activeFrom",
              "dataitem_value" : "01-11-2025"
            },
            {
              "dataitem_name" : "Phase",
              "dataitem_value" : "NCTS"
            },
            {
              "dataitem_name" : "Domain",
              "dataitem_value" : "6"
            }
          ],
          "language" : [
            {
              "lang_code" : "en",
              "lang_desc" : "Luggage"
            }
          ]
        }
      ],
      "languagecode" : "EN",
      "snapshotversion" : 2
    }
  ],
  "links" : [
    {
      "rel" : "self",
      "href" : "https://vdp.nonprod.denodo.hip.ns2n.corp.hmrc.gov.uk:9443/server/central_reference_data_library/ws_iv_crdl_reference_data/views/iv_crdl_reference_data?%24orderby=snapshotversion+ASC&code_list_code=CL017&%24count=10"
    },
    {
      "title" : "Previous interval",
      "rel" : "prev",
      "href" : "?%24start_index=150&%24orderby=snapshotversion+ASC&code_list_code=CL017&%24count=10"
    },
    {
      "title" : "Next interval",
      "rel" : "next",
      "href" : "?%24start_index=170&%24orderby=snapshotversion+ASC&code_list_code=CL017&%24count=10"
    }
  ]
}